trakai/__init__.py
trakai/__main__.py
trakai/build.py
trakai/output.py
trakai/parsing.py
trakai/utils.py
trakai/version.py
trakai/templates/excerpt.html
trakai/templates/feed.xml
trakai/templates/list.html
trakai/templates/page.html
trakai/templates/post.html
trakai-0.2.4.dist-info/LICENSE.txt
trakai-0.2.4.dist-info/METADATA
trakai-0.2.4.dist-info/WHEEL
trakai-0.2.4.dist-info/entry_points.txt
trakai-0.2.4.dist-info/top_level.txt
trakai-0.2.4.dist-info/RECORD
