Metadata-Version: 2.1
Name: trakai
Version: 0.2.4
Summary: A simple blog generator designed specially to integrate into existing sites.
Home-page: https://novov.neocities.org/projects/trakai.html
Author: novov
Author-email: anon185441@gmail.com
License: MIT
Platform: UNKNOWN
Classifier: Programming Language :: Python :: 3
Classifier: License :: OSI Approved :: MIT License
Classifier: Operating System :: OS Independent
Classifier: Development Status :: 3 - Alpha
Classifier: Topic :: Internet :: WWW/HTTP
Classifier: Topic :: Internet :: WWW/HTTP :: Site Management
Requires-Python: >=3.6
Requires-Dist: jinja2 (>=2.11.0)
Requires-Dist: markdown (>=3.3.0)
